annotator/__init__.py
annotator/example.py
annotator/frontend/dist/index.html
annotator/frontend/dist/assets/browser-BGtEBiJZ.js
annotator/frontend/dist/assets/index-DrBqgfis.css
annotator/frontend/dist/assets/index-O_eoPyqU.js
streamlit_custom_componentt-0.0.2.dist-info/LICENSE
streamlit_custom_componentt-0.0.2.dist-info/METADATA
streamlit_custom_componentt-0.0.2.dist-info/WHEEL
streamlit_custom_componentt-0.0.2.dist-info/top_level.txt
streamlit_custom_componentt-0.0.2.dist-info/RECORD
